synth_machine/__init__.py
synth_machine/cost.py
synth_machine/executor_factory.py
synth_machine/executors/__init__.py
synth_machine/executors/anthropic.py
synth_machine/executors/base.py
synth_machine/executors/lorem.py
synth_machine/executors/openai.py
synth_machine/executors/togetherai.py
synth_machine/experimental/synth_test/__init__.py
synth_machine/experimental/synth_test/run.py
synth_machine/experimental/synth_test/synth_test_config.py
synth_machine/experimental/synth_test/synth_test_prompts.py
synth_machine/experimental/synth_test/synth_test_runner.py
synth_machine/machine.py
synth_machine/machine_config.py
synth_machine/operator_setup.py
synth_machine/rag.py
synth_machine/runners.py
synth_machine/synth_definition.py
synth_machine/tools.py
synth_machine/user_defined_functions.py
synth_machine-0.6.1.dist-info/LICENSE
synth_machine-0.6.1.dist-info/METADATA
synth_machine-0.6.1.dist-info/WHEEL
synth_machine-0.6.1.dist-info/RECORD
