Metadata-Version: 2.1
Name: synth_machine
Version: 0.6.1
Summary: 
License: GPL-3.0-or-later
Author: David
Author-email: david@hiresynth.ai
Requires-Python: >=3.10,<3.13
Classifier: License :: OSI Approved :: GNU General Public License v3 or later (GPLv3+)
Classifier: Programming Language :: Python :: 3
Classifier: Programming Language :: Python :: 3.10
Classifier: Programming Language :: Python :: 3.11
Classifier: Programming Language :: Python :: 3.12
Provides-Extra: anthropic
Provides-Extra: openai
Provides-Extra: togetherai
Requires-Dist: aenum (>=3.1.15,<4.0.0)
Requires-Dist: anthropic (>=0.30.0,<0.31.0) ; extra == "anthropic"
Requires-Dist: hiresynth-object-store-python (>=0.1.4,<0.2.0)
Requires-Dist: httpx (>=0.27.0,<0.28.0)
Requires-Dist: jinja2 (>=3.1.2,<4.0.0)
Requires-Dist: jq (>=1.6.0,<2.0.0)
Requires-Dist: jsonschema (>=4.19.2,<5.0.0)
Requires-Dist: magika (>=0.5.1,<0.6.0)
Requires-Dist: openai (==1.35.10) ; extra == "openai" or extra == "togetherai"
Requires-Dist: partial_json_parser
Requires-Dist: pydantic (>=2.7.1,<3.0.0)
Requires-Dist: requests (>=2.31.0,<3.0.0)
Requires-Dist: tiktoken (==0.6.0)
Requires-Dist: together (>=1.2.1,<2.0.0) ; extra == "togetherai"
Requires-Dist: transitions (>=0.9.0,<0.10.0)
